CageCavityCalc/CageCavityCalc.py
CageCavityCalc/__init__.py
CageCavityCalc/__main__.py
CageCavityCalc/calculations.py
CageCavityCalc/data.py
CageCavityCalc/electrostatics.py
CageCavityCalc/grid_classes.py
CageCavityCalc/hydrophobicity.py
CageCavityCalc/input_output.py
CageCavityCalc/log.py
CageCavityCalc/window_size.py
CageCavityCalc/examples/10_mdanalysis_hydrophobicity/cage.gro
CageCavityCalc/examples/10_mdanalysis_hydrophobicity/cage_cavity.pdb
CageCavityCalc/examples/10_mdanalysis_hydrophobicity/example_10.py
CageCavityCalc/examples/11_errors/example_11.py
CageCavityCalc/examples/12_test_cage/fig_1.png
CageCavityCalc/examples/12_test_cage/fig_2.png
CageCavityCalc/examples/12_test_cage/fig_3.png
CageCavityCalc/examples/12_test_cage/fig_4.png
CageCavityCalc/examples/12_test_cage/fig_5.png
CageCavityCalc/examples/12_test_cage/fig_6.png
CageCavityCalc/examples/12_test_cage/test.mol2
CageCavityCalc/examples/12_test_cage/test.pdb
CageCavityCalc/examples/12_test_cage/test.spartan
CageCavityCalc/examples/12_test_cage/test_box_cavity.pdb
CageCavityCalc/examples/12_test_cage/test_cavity.pdb
CageCavityCalc/examples/12_test_cage/test_cavity.pml
CageCavityCalc/examples/12_test_cage/test_cavity.pse
CageCavityCalc/examples/12_test_cage/test_cavity_vol_calc.txt
CageCavityCalc/examples/12_test_cage/test_extra_data.txt
CageCavityCalc/examples/12_test_cage/test_hydrophobicity_cavity_dummy_atoms.txt
CageCavityCalc/examples/13_cages_review/1148701.pdb
CageCavityCalc/examples/13_cages_review/1148701_cavity.pdb
CageCavityCalc/examples/13_cages_review/1148701_cavity.pml
CageCavityCalc/examples/13_cages_review/210396.pdb
CageCavityCalc/examples/13_cages_review/210396_cavity.pdb
CageCavityCalc/examples/13_cages_review/210396_cavity.pml
CageCavityCalc/examples/13_cages_review/218828.pdb
CageCavityCalc/examples/13_cages_review/218828_cavity.pdb
CageCavityCalc/examples/13_cages_review/218828_cavity.pml
CageCavityCalc/examples/13_cages_review/41586_2016_BFnature20771_MOESM527_ESM.pdb
CageCavityCalc-1.0.5.dist-info/LICENSE
CageCavityCalc-1.0.5.dist-info/METADATA
CageCavityCalc-1.0.5.dist-info/WHEEL
CageCavityCalc-1.0.5.dist-info/entry_points.txt
CageCavityCalc-1.0.5.dist-info/top_level.txt
CageCavityCalc-1.0.5.dist-info/RECORD
